someutils/__init__.py
someutils/images.py
someutils/paths.py
someutils-0.4.3.dist-info/METADATA
someutils-0.4.3.dist-info/RECORD
someutils-0.4.3.dist-info/WHEEL
someutils-0.4.3.dist-info/top_level.txt
