Metadata-Version: 2.1
Name: someutils
Version: 0.4.3
Summary: Various utilities for Python
Home-page: https://gitlab.com/flow.gunso/someutils
Author: flow.gunso
Author-email: flow.gunso@gmail.com
License: UNKNOWN
Platform: UNKNOWN
Classifier: Intended Audience :: Developers
Classifier: License :: OSI Approved :: Mozilla Public License 2.0 (MPL 2.0)
Classifier: Operating System :: OS Independent
Classifier: Programming Language :: Python
Classifier: Topic :: Multimedia :: Graphics
Classifier: Topic :: Software Development :: Libraries :: Python Modules
Classifier: Topic :: System
Classifier: Topic :: Utilities
Requires-Dist: exifread
Requires-Dist: Pillow
Requires-Dist: pathlib
